golemio/__init__.py
golemio/client.py
golemio/errors.py
golemic_pid_api-0.1.dist-info/LICENSE
golemic_pid_api-0.1.dist-info/METADATA
golemic_pid_api-0.1.dist-info/WHEEL
golemic_pid_api-0.1.dist-info/top_level.txt
golemic_pid_api-0.1.dist-info/RECORD
